<?xml version = '1.0' encoding = 'UTF-8'?>
<Diagram class="oracle.dbtools.crest.swingui.relational.DPVRelational" name="Relational_1" id="342E1020-2B6C-BB59-CA1C-3CF0F8FD497A">
<createdBy>ortiz</createdBy>
<modifiedBy>ortiz</modifiedBy>
<createdTime>2025-03-16 02:10:48 UTC</createdTime>
<autoRoute>false</autoRoute>
<boxInbox>true</boxInbox>
<showLegend>false</showLegend>
<showLabels>false</showLabels>
<showRelAttributes>false</showRelAttributes>
<gridEnabled>false</gridEnabled>
<showGrid>false</showGrid>
<diagramColor>-1</diagramColor>
<display>false</display>
<notation>1</notation>
<objectViews>
<OView class="oracle.dbtools.crest.swingui.relational.TVTable" oid="027079F2-CD62-3587-AD67-3D5A9B16CD70" otype="Table" vid="19A6ABF9-30CC-30B6-5DD8-036627470415">
<hideElementsInCurrentOnly>false</hideElementsInCurrentOnly>
<bounds x="519" y="311" width="170" height="111"/>
</OView>
<OView class="oracle.dbtools.crest.swingui.relational.TVTable" oid="0807E71F-C969-A701-4451-532234534C79" otype="Table" vid="69DB63B9-7E04-31B4-0DEA-C5D493F00B4E">
<hideElementsInCurrentOnly>false</hideElementsInCurrentOnly>
<bounds x="44" y="43" width="170" height="110"/>
</OView>
<OView class="oracle.dbtools.crest.swingui.relational.TVTable" oid="135671D6-BC95-D5CC-237E-F399F9A1DB44" otype="Table" vid="CA952698-B256-4070-0A96-EBCA4C91B815">
<hideElementsInCurrentOnly>false</hideElementsInCurrentOnly>
<bounds x="449" y="786" width="170" height="110"/>
</OView>
<OView class="oracle.dbtools.crest.swingui.relational.TVTable" oid="162F44CB-09D5-4AB0-999C-87F10920C135" otype="Table" vid="FB4C6460-6F58-5F09-9284-10398DF2383A">
<hideElementsInCurrentOnly>false</hideElementsInCurrentOnly>
<bounds x="460" y="600" width="170" height="110"/>
</OView>
<OView class="oracle.dbtools.crest.swingui.relational.TVTable" oid="27548C3D-2B66-8792-1EA7-B0BC3F28F509" otype="Table" vid="152605B6-F675-FC67-364D-2E1A01188FFA">
<hideElementsInCurrentOnly>false</hideElementsInCurrentOnly>
<bounds x="209" y="634" width="170" height="110"/>
</OView>
<OView class="oracle.dbtools.crest.swingui.relational.TVTable" oid="4676E32C-0F07-0EA4-8A92-8C72819C49D2" otype="Table" vid="C75FFD1C-D0F5-DB57-3CC2-70B5632A5584">
<hideElementsInCurrentOnly>false</hideElementsInCurrentOnly>
<bounds x="719" y="478" width="170" height="111"/>
</OView>
<OView class="oracle.dbtools.crest.swingui.relational.TVTable" oid="7161C68B-F096-39F9-50CD-92D9C89A3797" otype="Table" vid="4004F960-0985-6713-EC06-50BA02ABF4DA">
<hideElementsInCurrentOnly>false</hideElementsInCurrentOnly>
<bounds x="1423" y="265" width="170" height="127"/>
</OView>
<OView class="oracle.dbtools.crest.swingui.relational.TVTable" oid="8446DBAF-1FEF-10B9-4506-E6AF51EC6FF1" otype="Table" vid="0D4BF55C-8C5B-444D-56B0-3EEC6B715F54">
<hideElementsInCurrentOnly>false</hideElementsInCurrentOnly>
<bounds x="4" y="765" width="313" height="169"/>
</OView>
<OView class="oracle.dbtools.crest.swingui.relational.TVTable" oid="87E759F1-2909-BEA9-C49D-8E5AE8B61C0C" otype="Table" vid="804D0A29-F45A-041D-5C27-1FFB59B030CC">
<hideElementsInCurrentOnly>false</hideElementsInCurrentOnly>
<bounds x="799" y="87" width="170" height="111"/>
</OView>
<OView class="oracle.dbtools.crest.swingui.relational.TVTable" oid="A4F8975C-3910-7951-6FA0-6CA7486DF35E" otype="Table" vid="1125DA05-704F-2A18-5E20-976516B3A10E">
<hideElementsInCurrentOnly>false</hideElementsInCurrentOnly>
<bounds x="738" y="255" width="170" height="190"/>
</OView>
<OView class="oracle.dbtools.crest.swingui.relational.TVTable" oid="B3258E0B-6B32-1D2F-EB5B-553FF13362D3" otype="Table" vid="4F918610-7E38-0BB1-F3E0-4C6D17E59AD7">
<hideElementsInCurrentOnly>false</hideElementsInCurrentOnly>
<bounds x="5" y="405" width="170" height="110"/>
</OView>
<OView class="oracle.dbtools.crest.swingui.relational.TVTable" oid="C45001D6-0A01-2883-B8D0-F8B41CC5110A" otype="Table" vid="070928E9-3F06-59AA-59A9-3593BDD8B6B2">
<hideElementsInCurrentOnly>false</hideElementsInCurrentOnly>
<bounds x="1086" y="277" width="170" height="143"/>
</OView>
<OView class="oracle.dbtools.crest.swingui.relational.TVTable" oid="CF8E289D-3067-4E3E-646B-6FBE5F92A996" otype="Table" vid="772CA1E7-159A-02C4-CEE2-FD5A40CF8500">
<hideElementsInCurrentOnly>false</hideElementsInCurrentOnly>
<bounds x="290" y="259" width="170" height="111"/>
</OView>
<OView class="oracle.dbtools.crest.swingui.relational.TVTable" oid="D4819341-44F7-CB1D-EE3C-4CCEEEC81449" otype="Table" vid="0E5D01D7-B8C2-25EF-43CD-55BFDAB6D23B">
<hideElementsInCurrentOnly>false</hideElementsInCurrentOnly>
<bounds x="967" y="584" width="170" height="167"/>
</OView>
<OView class="oracle.dbtools.crest.swingui.relational.TVTable" oid="E078B434-E809-F796-FB01-C5B95200627E" otype="Table" vid="1540A30C-5252-0B05-208A-202097067253">
<hideElementsInCurrentOnly>false</hideElementsInCurrentOnly>
<bounds x="463" y="173" width="170" height="110"/>
</OView>
<OView class="oracle.dbtools.crest.swingui.relational.TVTable" oid="E12BCD6A-D3FE-056B-03F6-6DE3303EC280" otype="Table" vid="FEB72758-BF45-E108-C8F9-67D00D4BA891">
<hideElementsInCurrentOnly>false</hideElementsInCurrentOnly>
<bounds x="13" y="204" width="170" height="110"/>
</OView>
<OView class="oracle.dbtools.crest.swingui.relational.TVTable" oid="F1801991-0D08-E387-0205-BF20D219A5FD" otype="Table" vid="5436DD1D-4044-0F53-1A78-640877E5A8E4">
<hideElementsInCurrentOnly>false</hideElementsInCurrentOnly>
<bounds x="289" y="451" width="170" height="110"/>
</OView>
</objectViews>
<connectors>
<Connector class="oracle.dbtools.crest.swingui.relational.TVFKRelation" oid="1FA7D6AA-BC85-9C46-39C1-47644738E54F" otype="FKIndexAssociation" vid_source="19A6ABF9-30CC-30B6-5DD8-036627470415" vid_target="4004F960-0985-6713-EC06-50BA02ABF4DA">
<hideElementsInCurrentOnly>false</hideElementsInCurrentOnly>
<backgroundColor>-16777216</backgroundColor>
<lineWidth>1</lineWidth>
<points>
<point x="519" y="311"/>
<point x="455" y="122"/>
<point x="1423" y="265"/>
</points>
</Connector>
<Connector class="oracle.dbtools.crest.swingui.relational.TVFKRelation" oid="213E3B6F-59A7-D241-DA62-8E92D5BE004A" otype="FKIndexAssociation" vid_source="070928E9-3F06-59AA-59A9-3593BDD8B6B2" vid_target="FB4C6460-6F58-5F09-9284-10398DF2383A">
<hideElementsInCurrentOnly>false</hideElementsInCurrentOnly>
<backgroundColor>-16777216</backgroundColor>
<lineWidth>1</lineWidth>
<points>
<point x="1086" y="390"/>
<point x="630" y="613"/>
</points>
</Connector>
<Connector class="oracle.dbtools.crest.swingui.relational.TVFKRelation" oid="2348456D-C322-5A2E-D240-E2CD673B41C8" otype="FKIndexAssociation" vid_source="804D0A29-F45A-041D-5C27-1FFB59B030CC" vid_target="152605B6-F675-FC67-364D-2E1A01188FFA">
<hideElementsInCurrentOnly>false</hideElementsInCurrentOnly>
<backgroundColor>-16777216</backgroundColor>
<lineWidth>1</lineWidth>
<points>
<point x="824" y="198"/>
<point x="323" y="634"/>
</points>
</Connector>
<Connector class="oracle.dbtools.crest.swingui.relational.TVFKRelation" oid="2BE45262-4536-018F-6944-54DE09BDEE72" otype="FKIndexAssociation" vid_source="0E5D01D7-B8C2-25EF-43CD-55BFDAB6D23B" vid_target="070928E9-3F06-59AA-59A9-3593BDD8B6B2">
<hideElementsInCurrentOnly>false</hideElementsInCurrentOnly>
<backgroundColor>-16777216</backgroundColor>
<lineWidth>1</lineWidth>
<points>
<point x="1111" y="584"/>
<point x="1111" y="420"/>
</points>
</Connector>
<Connector class="oracle.dbtools.crest.swingui.relational.TVFKRelation" oid="312B443E-D41E-BFC0-1BC6-28BE7AF11342" otype="FKIndexAssociation" vid_source="19A6ABF9-30CC-30B6-5DD8-036627470415" vid_target="5436DD1D-4044-0F53-1A78-640877E5A8E4">
<hideElementsInCurrentOnly>false</hideElementsInCurrentOnly>
<backgroundColor>-16777216</backgroundColor>
<lineWidth>1</lineWidth>
<points>
<point x="519" y="418"/>
<point x="459" y="454"/>
</points>
</Connector>
<Connector class="oracle.dbtools.crest.swingui.relational.TVFKRelation" oid="3A6E0D5E-E681-E236-D6BB-4E8A6B141FC8" otype="FKIndexAssociation" vid_source="0E5D01D7-B8C2-25EF-43CD-55BFDAB6D23B" vid_target="0E5D01D7-B8C2-25EF-43CD-55BFDAB6D23B">
<hideElementsInCurrentOnly>false</hideElementsInCurrentOnly>
<backgroundColor>-16777216</backgroundColor>
<lineWidth>1</lineWidth>
<points>
<point x="1137" y="584"/>
<point x="1155" y="461"/>
<point x="1155" y="532"/>
<point x="1060" y="532"/>
<point x="1060" y="584"/>
</points>
</Connector>
<Connector class="oracle.dbtools.crest.swingui.relational.TVFKRelation" oid="3DE65875-8BC0-446E-62AC-61BCB09E9B4A" otype="FKIndexAssociation" vid_source="772CA1E7-159A-02C4-CEE2-FD5A40CF8500" vid_target="0E5D01D7-B8C2-25EF-43CD-55BFDAB6D23B">
<hideElementsInCurrentOnly>false</hideElementsInCurrentOnly>
<backgroundColor>-16777216</backgroundColor>
<lineWidth>1</lineWidth>
<points>
<point x="290" y="259"/>
<point x="219" y="23"/>
<point x="1086" y="26"/>
<point x="1086" y="584"/>
</points>
</Connector>
<Connector class="oracle.dbtools.crest.swingui.relational.TVFKRelation" oid="460DB719-EA2D-6191-F117-8C9D094932A8" otype="FKIndexAssociation" vid_source="1125DA05-704F-2A18-5E20-976516B3A10E" vid_target="4F918610-7E38-0BB1-F3E0-4C6D17E59AD7">
<hideElementsInCurrentOnly>false</hideElementsInCurrentOnly>
<backgroundColor>-16777216</backgroundColor>
<lineWidth>1</lineWidth>
<points>
<point x="738" y="425"/>
<point x="175" y="425"/>
</points>
</Connector>
<Connector class="oracle.dbtools.crest.swingui.relational.TVFKRelation" oid="48D47790-2138-6B48-8AE3-21E266C7994E" otype="FKIndexAssociation" vid_source="1125DA05-704F-2A18-5E20-976516B3A10E" vid_target="070928E9-3F06-59AA-59A9-3593BDD8B6B2">
<hideElementsInCurrentOnly>false</hideElementsInCurrentOnly>
<backgroundColor>-16777216</backgroundColor>
<lineWidth>1</lineWidth>
<points>
<point x="908" y="363"/>
<point x="1086" y="363"/>
</points>
</Connector>
<Connector class="oracle.dbtools.crest.swingui.relational.TVFKRelation" oid="49119177-BD08-7A0F-A80F-BEE762FFE901" otype="FKIndexAssociation" vid_source="804D0A29-F45A-041D-5C27-1FFB59B030CC" vid_target="69DB63B9-7E04-31B4-0DEA-C5D493F00B4E">
<hideElementsInCurrentOnly>false</hideElementsInCurrentOnly>
<backgroundColor>-16777216</backgroundColor>
<lineWidth>1</lineWidth>
<points>
<point x="799" y="135"/>
<point x="214" y="135"/>
</points>
</Connector>
<Connector class="oracle.dbtools.crest.swingui.relational.TVFKRelation" oid="4E1D59C5-6FEE-BF31-06D5-CDC139EBCC87" otype="FKIndexAssociation" vid_source="0E5D01D7-B8C2-25EF-43CD-55BFDAB6D23B" vid_target="4004F960-0985-6713-EC06-50BA02ABF4DA">
<hideElementsInCurrentOnly>false</hideElementsInCurrentOnly>
<backgroundColor>-16777216</backgroundColor>
<lineWidth>1</lineWidth>
<points>
<point x="1078" y="584"/>
<point x="1145" y="372"/>
</points>
</Connector>
<Connector class="oracle.dbtools.crest.swingui.relational.TVFKRelation" oid="59FA7589-F2F8-B2C5-A844-91FEAA4EFF58" otype="FKIndexAssociation" vid_source="1125DA05-704F-2A18-5E20-976516B3A10E" vid_target="4004F960-0985-6713-EC06-50BA02ABF4DA">
<hideElementsInCurrentOnly>false</hideElementsInCurrentOnly>
<backgroundColor>-16777216</backgroundColor>
<lineWidth>1</lineWidth>
<points>
<point x="908" y="313"/>
<point x="1250" y="313"/>
</points>
</Connector>
<Connector class="oracle.dbtools.crest.swingui.relational.TVFKRelation" oid="5B8DEBAA-5038-BB62-3083-ACC03D2AB9F3" otype="FKIndexAssociation" vid_source="772CA1E7-159A-02C4-CEE2-FD5A40CF8500" vid_target="FEB72758-BF45-E108-C8F9-67D00D4BA891">
<hideElementsInCurrentOnly>false</hideElementsInCurrentOnly>
<backgroundColor>-16777216</backgroundColor>
<lineWidth>1</lineWidth>
<points>
<point x="290" y="286"/>
<point x="183" y="286"/>
</points>
</Connector>
<Connector class="oracle.dbtools.crest.swingui.relational.TVFKRelation" oid="5D02A379-C901-629E-A7BE-8F2718ED286B" otype="FKIndexAssociation" vid_source="0E5D01D7-B8C2-25EF-43CD-55BFDAB6D23B" vid_target="0E5D01D7-B8C2-25EF-43CD-55BFDAB6D23B">
<hideElementsInCurrentOnly>false</hideElementsInCurrentOnly>
<backgroundColor>-16777216</backgroundColor>
<lineWidth>1</lineWidth>
<points>
<point x="1137" y="649"/>
<point x="1187" y="649"/>
<point x="1188" y="776"/>
<point x="1052" y="777"/>
<point x="1052" y="751"/>
</points>
</Connector>
<Connector class="oracle.dbtools.crest.swingui.relational.TVFKRelation" oid="609633C9-DC29-FD84-1ACB-083ABDB558F6" otype="FKIndexAssociation" vid_source="0E5D01D7-B8C2-25EF-43CD-55BFDAB6D23B" vid_target="070928E9-3F06-59AA-59A9-3593BDD8B6B2">
<hideElementsInCurrentOnly>false</hideElementsInCurrentOnly>
<backgroundColor>-16777216</backgroundColor>
<lineWidth>1</lineWidth>
<points>
<point x="967" y="584"/>
<point x="868" y="463"/>
<point x="1086" y="420"/>
</points>
</Connector>
<Connector class="oracle.dbtools.crest.swingui.relational.TVFKRelation" oid="66223A42-D8BE-4035-A996-99035100C463" otype="FKIndexAssociation" vid_source="0E5D01D7-B8C2-25EF-43CD-55BFDAB6D23B" vid_target="C75FFD1C-D0F5-DB57-3CC2-70B5632A5584">
<hideElementsInCurrentOnly>false</hideElementsInCurrentOnly>
<backgroundColor>-16777216</backgroundColor>
<lineWidth>1</lineWidth>
<points>
<point x="1093" y="584"/>
<point x="1093" y="454"/>
<point x="889" y="478"/>
</points>
</Connector>
<Connector class="oracle.dbtools.crest.swingui.relational.TVFKRelation" oid="700BA483-B70C-3A9A-C3C6-EB3AB1A3DC9B" otype="FKIndexAssociation" vid_source="070928E9-3F06-59AA-59A9-3593BDD8B6B2" vid_target="CA952698-B256-4070-0A96-EBCA4C91B815">
<hideElementsInCurrentOnly>false</hideElementsInCurrentOnly>
<backgroundColor>-16777216</backgroundColor>
<lineWidth>1</lineWidth>
<points>
<point x="1086" y="414"/>
<point x="605" y="786"/>
</points>
</Connector>
<Connector class="oracle.dbtools.crest.swingui.relational.TVFKRelation" oid="76BFB766-CE15-7AFD-8796-C3D76AF62E28" otype="FKIndexAssociation" vid_source="070928E9-3F06-59AA-59A9-3593BDD8B6B2" vid_target="1540A30C-5252-0B05-208A-202097067253">
<hideElementsInCurrentOnly>false</hideElementsInCurrentOnly>
<backgroundColor>-16777216</backgroundColor>
<lineWidth>1</lineWidth>
<points>
<point x="1086" y="280"/>
<point x="633" y="280"/>
</points>
</Connector>
<Connector class="oracle.dbtools.crest.swingui.relational.TVFKRelation" oid="7BEEEA21-E3B1-A22F-438F-A4479BDBC4D1" otype="FKIndexAssociation" vid_source="804D0A29-F45A-041D-5C27-1FFB59B030CC" vid_target="CA952698-B256-4070-0A96-EBCA4C91B815">
<hideElementsInCurrentOnly>false</hideElementsInCurrentOnly>
<backgroundColor>-16777216</backgroundColor>
<lineWidth>1</lineWidth>
<points>
<point x="856" y="198"/>
<point x="561" y="786"/>
</points>
</Connector>
<Connector class="oracle.dbtools.crest.swingui.relational.TVFKRelation" oid="7E0ED1F2-150B-D2D4-FDC0-53315025FF64" otype="FKIndexAssociation" vid_source="1125DA05-704F-2A18-5E20-976516B3A10E" vid_target="0D4BF55C-8C5B-444D-56B0-3EEC6B715F54">
<hideElementsInCurrentOnly>false</hideElementsInCurrentOnly>
<backgroundColor>-16777216</backgroundColor>
<lineWidth>1</lineWidth>
<points>
<point x="738" y="414"/>
<point x="272" y="765"/>
</points>
</Connector>
<Connector class="oracle.dbtools.crest.swingui.relational.TVFKRelation" oid="871F7895-15A2-E54F-DC63-D4CBA15EE589" otype="FKIndexAssociation" vid_source="4004F960-0985-6713-EC06-50BA02ABF4DA" vid_target="FB4C6460-6F58-5F09-9284-10398DF2383A">
<hideElementsInCurrentOnly>false</hideElementsInCurrentOnly>
<backgroundColor>-16777216</backgroundColor>
<lineWidth>1</lineWidth>
<points>
<point x="1423" y="357"/>
<point x="630" y="626"/>
</points>
</Connector>
<Connector class="oracle.dbtools.crest.swingui.relational.TVFKRelation" oid="90B87ADA-B1DE-0C06-F08C-0866F3E393DC" otype="FKIndexAssociation" vid_source="804D0A29-F45A-041D-5C27-1FFB59B030CC" vid_target="5436DD1D-4044-0F53-1A78-640877E5A8E4">
<hideElementsInCurrentOnly>false</hideElementsInCurrentOnly>
<backgroundColor>-16777216</backgroundColor>
<lineWidth>1</lineWidth>
<points>
<point x="806" y="198"/>
<point x="451" y="451"/>
</points>
</Connector>
<Connector class="oracle.dbtools.crest.swingui.relational.TVFKRelation" oid="94CDAEA9-C48A-60DC-228A-EA5765CE6607" otype="FKIndexAssociation" vid_source="804D0A29-F45A-041D-5C27-1FFB59B030CC" vid_target="C75FFD1C-D0F5-DB57-3CC2-70B5632A5584">
<hideElementsInCurrentOnly>false</hideElementsInCurrentOnly>
<backgroundColor>-16777216</backgroundColor>
<lineWidth>1</lineWidth>
<points>
<point x="844" y="198"/>
<point x="844" y="478"/>
</points>
</Connector>
<Connector class="oracle.dbtools.crest.swingui.relational.TVFKRelation" oid="9BBC741C-3555-D09C-F1CF-37E95D7F217F" otype="FKIndexAssociation" vid_source="19A6ABF9-30CC-30B6-5DD8-036627470415" vid_target="4F918610-7E38-0BB1-F3E0-4C6D17E59AD7">
<hideElementsInCurrentOnly>false</hideElementsInCurrentOnly>
<backgroundColor>-16777216</backgroundColor>
<lineWidth>1</lineWidth>
<points>
<point x="519" y="413"/>
<point x="175" y="413"/>
</points>
</Connector>
<Connector class="oracle.dbtools.crest.swingui.relational.TVFKRelation" oid="AA2AF2B1-CF85-A8DE-9487-109C9FF0F735" otype="FKIndexAssociation" vid_source="1125DA05-704F-2A18-5E20-976516B3A10E" vid_target="070928E9-3F06-59AA-59A9-3593BDD8B6B2">
<hideElementsInCurrentOnly>false</hideElementsInCurrentOnly>
<backgroundColor>-16777216</backgroundColor>
<lineWidth>1</lineWidth>
<points>
<point x="908" y="348"/>
<point x="1086" y="348"/>
</points>
</Connector>
<Connector class="oracle.dbtools.crest.swingui.relational.TVFKRelation" oid="AEE63BA2-A15A-A9DB-AC91-190179005C8A" otype="FKIndexAssociation" vid_source="19A6ABF9-30CC-30B6-5DD8-036627470415" vid_target="C75FFD1C-D0F5-DB57-3CC2-70B5632A5584">
<hideElementsInCurrentOnly>false</hideElementsInCurrentOnly>
<backgroundColor>-16777216</backgroundColor>
<lineWidth>1</lineWidth>
<points>
<point x="670" y="422"/>
<point x="737" y="478"/>
</points>
</Connector>
<Connector class="oracle.dbtools.crest.swingui.relational.TVFKRelation" oid="B66DC7D9-19B1-240C-917C-3A5314FCF7F1" otype="FKIndexAssociation" vid_source="0E5D01D7-B8C2-25EF-43CD-55BFDAB6D23B" vid_target="4004F960-0985-6713-EC06-50BA02ABF4DA">
<hideElementsInCurrentOnly>false</hideElementsInCurrentOnly>
<backgroundColor>-16777216</backgroundColor>
<lineWidth>1</lineWidth>
<points>
<point x="1051" y="584"/>
<point x="1051" y="122"/>
<point x="1423" y="265"/>
</points>
</Connector>
<Connector class="oracle.dbtools.crest.swingui.relational.TVFKRelation" oid="B783EB76-3452-8177-A869-EFF5E73DECE4" otype="FKIndexAssociation" vid_source="1125DA05-704F-2A18-5E20-976516B3A10E" vid_target="4004F960-0985-6713-EC06-50BA02ABF4DA">
<hideElementsInCurrentOnly>false</hideElementsInCurrentOnly>
<backgroundColor>-16777216</backgroundColor>
<lineWidth>1</lineWidth>
<points>
<point x="908" y="313"/>
<point x="1423" y="313"/>
</points>
</Connector>
<Connector class="oracle.dbtools.crest.swingui.relational.TVFKRelation" oid="BF74CA02-980B-BC1B-526B-24DE78A92E5D" otype="FKIndexAssociation" vid_source="804D0A29-F45A-041D-5C27-1FFB59B030CC" vid_target="1540A30C-5252-0B05-208A-202097067253">
<hideElementsInCurrentOnly>false</hideElementsInCurrentOnly>
<backgroundColor>-16777216</backgroundColor>
<lineWidth>1</lineWidth>
<points>
<point x="799" y="185"/>
<point x="633" y="185"/>
</points>
</Connector>
<Connector class="oracle.dbtools.crest.swingui.relational.TVFKRelation" oid="D4E56E8C-EF05-F0A7-C802-5C83BD8810CD" otype="FKIndexAssociation" vid_source="19A6ABF9-30CC-30B6-5DD8-036627470415" vid_target="FEB72758-BF45-E108-C8F9-67D00D4BA891">
<hideElementsInCurrentOnly>false</hideElementsInCurrentOnly>
<backgroundColor>-16777216</backgroundColor>
<lineWidth>1</lineWidth>
<points>
<point x="519" y="312"/>
<point x="183" y="312"/>
</points>
</Connector>
<Connector class="oracle.dbtools.crest.swingui.relational.TVFKRelation" oid="DAF1AF6A-8D45-F1F8-675B-1AA1EF4B6C1B" otype="FKIndexAssociation" vid_source="19A6ABF9-30CC-30B6-5DD8-036627470415" vid_target="0D4BF55C-8C5B-444D-56B0-3EEC6B715F54">
<hideElementsInCurrentOnly>false</hideElementsInCurrentOnly>
<backgroundColor>-16777216</backgroundColor>
<lineWidth>1</lineWidth>
<points>
<point x="553" y="422"/>
<point x="238" y="765"/>
</points>
</Connector>
<Connector class="oracle.dbtools.crest.swingui.relational.TVFKRelation" oid="E0068DB7-5CF2-6E11-244A-456586BFC3D3" otype="FKIndexAssociation" vid_source="1125DA05-704F-2A18-5E20-976516B3A10E" vid_target="69DB63B9-7E04-31B4-0DEA-C5D493F00B4E">
<hideElementsInCurrentOnly>false</hideElementsInCurrentOnly>
<backgroundColor>-16777216</backgroundColor>
<lineWidth>1</lineWidth>
<points>
<point x="738" y="319"/>
<point x="214" y="113"/>
</points>
</Connector>
<Connector class="oracle.dbtools.crest.swingui.relational.TVFKRelation" oid="ED104280-EC34-15D7-59B6-9B7412645DF0" otype="FKIndexAssociation" vid_source="804D0A29-F45A-041D-5C27-1FFB59B030CC" vid_target="4004F960-0985-6713-EC06-50BA02ABF4DA">
<hideElementsInCurrentOnly>false</hideElementsInCurrentOnly>
<backgroundColor>-16777216</backgroundColor>
<lineWidth>1</lineWidth>
<points>
<point x="799" y="198"/>
<point x="93" y="410"/>
<point x="91" y="87"/>
<point x="1423" y="265"/>
</points>
</Connector>
<Connector class="oracle.dbtools.crest.swingui.relational.TVFKRelation" oid="EE81C0D5-4635-F0D4-C65C-EB83532CADEA" otype="FKIndexAssociation" vid_source="19A6ABF9-30CC-30B6-5DD8-036627470415" vid_target="152605B6-F675-FC67-364D-2E1A01188FFA">
<hideElementsInCurrentOnly>false</hideElementsInCurrentOnly>
<backgroundColor>-16777216</backgroundColor>
<lineWidth>1</lineWidth>
<points>
<point x="550" y="422"/>
<point x="346" y="634"/>
</points>
</Connector>
<Connector class="oracle.dbtools.crest.swingui.relational.TVFKRelation" oid="FD186A5B-7D14-0999-95AE-BF25D9946DD4" otype="FKIndexAssociation" vid_source="1125DA05-704F-2A18-5E20-976516B3A10E" vid_target="C75FFD1C-D0F5-DB57-3CC2-70B5632A5584">
<hideElementsInCurrentOnly>false</hideElementsInCurrentOnly>
<backgroundColor>-16777216</backgroundColor>
<lineWidth>1</lineWidth>
<points>
<point x="813" y="445"/>
<point x="813" y="478"/>
</points>
</Connector>
<Connector class="oracle.dbtools.crest.swingui.relational.TVFKRelation" oid="FEB6D08A-2640-76D4-AA1E-060237B72660" otype="FKIndexAssociation" vid_source="070928E9-3F06-59AA-59A9-3593BDD8B6B2" vid_target="4004F960-0985-6713-EC06-50BA02ABF4DA">
<hideElementsInCurrentOnly>false</hideElementsInCurrentOnly>
<backgroundColor>-16777216</backgroundColor>
<lineWidth>1</lineWidth>
<points>
<point x="1256" y="334"/>
<point x="1250" y="334"/>
</points>
</Connector>
</connectors>
</Diagram>
